dbt/adapters/database/__init__.py
dbt/adapters/database/__version__.py
dbt/adapters/database/column.py
dbt/adapters/database/connections.py
dbt/adapters/database/impl.py
dbt/adapters/database/relation.py
dbt/adapters/database/record/__init__.py
dbt/adapters/database/record/handle.py
dbt/adapters/database/record/cursor/cursor.py
dbt/adapters/database/record/cursor/status.py
dbt/adapters/database/relation_configs/__init__.py
dbt/adapters/database/relation_configs/constants.py
dbt/adapters/database/relation_configs/index.py
dbt/adapters/database/relation_configs/materialized_view.py
dbt/include/database/__init__.py
dbt/include/database/dbt_project.yml
dbt/include/database/profile_template.yml
dbt/include/database/sample_profiles.yml
dbt/include/database/macros/adapters.sql
dbt/include/database/macros/catalog.sql
dbt/include/database/macros/relations.sql
dbt/include/database/macros/timestamps.sql
dbt/include/database/macros/materializations/incremental_strategies.sql
dbt/include/database/macros/materializations/snapshot_merge.sql
dbt/include/database/macros/relations/materialized_view/alter.sql
dbt/include/database/macros/relations/materialized_view/create.sql
dbt/include/database/macros/relations/materialized_view/describe.sql
dbt/include/database/macros/relations/materialized_view/drop.sql
dbt/include/database/macros/relations/materialized_view/refresh.sql
dbt/include/database/macros/relations/materialized_view/rename.sql
dbt/include/database/macros/relations/table/drop.sql
dbt/include/database/macros/relations/table/rename.sql
dbt/include/database/macros/relations/table/replace.sql
dbt/include/database/macros/relations/view/drop.sql
dbt/include/database/macros/relations/view/rename.sql
dbt/include/database/macros/relations/view/replace.sql
dbt/include/database/macros/utils/any_value.sql
dbt/include/database/macros/utils/columns_spec_ddl.sql
dbt/include/database/macros/utils/dateadd.sql
dbt/include/database/macros/utils/datediff.sql
dbt_dbs-0.0.1.dist-info/METADATA
dbt_dbs-0.0.1.dist-info/WHEEL
dbt_dbs-0.0.1.dist-info/RECORD
